easey.py
easey-0.1.0.dist-info/licenses/LICENSE
easey-0.1.0.dist-info/METADATA
easey-0.1.0.dist-info/WHEEL
easey-0.1.0.dist-info/top_level.txt
easey-0.1.0.dist-info/RECORD
