Metadata-Version: 2.4
Name: easey
Version: 0.1.0
Summary: A minimal implementation of Embarrassingly Shallow Autoencoders
Author-email: George Brown <gcbrown@pm.me>
License-Expression: MIT
Project-URL: Homepage, https://github.com/gcbrown/easey
Project-URL: Issues, https://github.com/gcbrown/easey/issues
Classifier: Programming Language :: Python :: 3
Classifier: Operating System :: OS Independent
Requires-Python: >=3.10
License-File: LICENSE
Requires-Dist: numpy>=2.0
Requires-Dist: sparse-dot-mkl>=0.9
Dynamic: license-file
